chemiscope/__init__.py
chemiscope/input.py
chemiscope/jupyter.py
chemiscope/main.py
chemiscope/version.py
chemiscope/explore/__init__.py
chemiscope/explore/_metatomic.py
chemiscope/sphinx/__init__.py
chemiscope/sphinx/directive.py
chemiscope/sphinx/file_path_iterator.py
chemiscope/sphinx/nodes.py
chemiscope/sphinx/scraper.py
chemiscope/sphinx/utils.py
chemiscope/sphinx/static/.gitignore
chemiscope/sphinx/static/chemiscope-loading.svg
chemiscope/sphinx/static/chemiscope-sphinx.css
chemiscope/sphinx/static/chemiscope-sphinx.html
chemiscope/sphinx/static/chemiscope-sphinx.js
chemiscope/sphinx/static/chemiscope.min.js
chemiscope/streamlit/__init__.py
chemiscope/streamlit/chemiscope-streamlit.min.js
chemiscope/streamlit/index.html
chemiscope/structures/__init__.py
chemiscope/structures/_ase.py
chemiscope/structures/_mda.py
chemiscope/structures/_shapes.py
chemiscope/structures/_stk.py
chemiscope-0.9.0.data/data/etc/jupyter/nbconfig/notebook.d/chemiscope.json
chemiscope-0.9.0.data/data/share/jupyter/labextensions/chemiscope/install.json
chemiscope-0.9.0.data/data/share/jupyter/labextensions/chemiscope/package.json
chemiscope-0.9.0.data/data/share/jupyter/labextensions/chemiscope/static/305.8c2f3e46b4fc15c5e159.js
chemiscope-0.9.0.data/data/share/jupyter/labextensions/chemiscope/static/78.ee51bbe99bbadc363a75.js
chemiscope-0.9.0.data/data/share/jupyter/labextensions/chemiscope/static/78.ee51bbe99bbadc363a75.js.LICENSE.txt
chemiscope-0.9.0.data/data/share/jupyter/labextensions/chemiscope/static/841.0a01a758cae95d42945f.js
chemiscope-0.9.0.data/data/share/jupyter/labextensions/chemiscope/static/remoteEntry.a5576bb9bd5866f9ecbb.js
chemiscope-0.9.0.data/data/share/jupyter/labextensions/chemiscope/static/style.js
chemiscope-0.9.0.data/data/share/jupyter/labextensions/chemiscope/static/third-party-licenses.json
chemiscope-0.9.0.data/data/share/jupyter/nbextensions/chemiscope/chemiscope.min.js
chemiscope-0.9.0.data/data/share/jupyter/nbextensions/chemiscope/extension.js
chemiscope-0.9.0.dist-info/licenses/LICENSE
chemiscope-0.9.0.dist-info/METADATA
chemiscope-0.9.0.dist-info/WHEEL
chemiscope-0.9.0.dist-info/entry_points.txt
chemiscope-0.9.0.dist-info/top_level.txt
chemiscope-0.9.0.dist-info/RECORD
