Metadata-Version: 2.4
Name: chemiscope
Version: 0.9.0
Summary: Helpers to work with the chemiscope interactive structure/property explorer for materials and molecules
Author-email: Guillaume Fraux <guillaume.fraux@epfl.ch>
License: BSD-3-Clause
Project-URL: homepage, https://chemiscope.org
Project-URL: documentation, https://chemiscope.org/docs/
Project-URL: repository, https://github.com/lab-cosmo/chemiscope
Keywords: visualization,materials science,chemistry,molecules
Classifier: Development Status :: 4 - Beta
Classifier: Environment :: Console
Classifier: Intended Audience :: Developers
Classifier: Intended Audience :: Science/Research
Classifier: License :: OSI Approved :: BSD License
Classifier: Operating System :: OS Independent
Classifier: Topic :: Scientific/Engineering
Classifier: Topic :: Scientific/Engineering :: Chemistry
Classifier: Topic :: Scientific/Engineering :: Physics
Classifier: Topic :: Scientific/Engineering :: Visualization
Requires-Python: >=3.10
License-File: LICENSE
Requires-Dist: numpy
Requires-Dist: ipywidgets<9,>=7
Provides-Extra: explore
Requires-Dist: pet_mad<2.0,>=1.4; extra == "explore"
Requires-Dist: metatomic-torch<0.2,>=0.1.0; extra == "explore"
Requires-Dist: vesin<0.4,>=0.3.5; extra == "explore"
Provides-Extra: streamlit
Requires-Dist: streamlit>=1.25; extra == "streamlit"
Dynamic: license-file
